farbencounter/README.MD
farbencounter/__init__.py
farbencounter/requirements.txt
farbencounter/thirdparty.json
farbencounter-0.10.dist-info/LICENSE.rst
farbencounter-0.10.dist-info/METADATA
farbencounter-0.10.dist-info/WHEEL
farbencounter-0.10.dist-info/top_level.txt
farbencounter-0.10.dist-info/RECORD
