Metadata-Version: 2.1
Name: farbencounter
Version: 0.10
Summary: Counts the unique colors in an image and returns a DataFrame with color counts and optional color coordinates.
Home-page: https://github.com/hansalemaos/farbencounter
Author: Johannes Fischer
Author-email: aulasparticularesdealemaosp@gmail.com
License: MIT
Keywords: count,colours,colors,rgb,numpy
Classifier: Development Status :: 4 - Beta
Classifier: Programming Language :: Python :: 3 :: Only
Classifier: Programming Language :: Python :: 3.10
Classifier: Topic :: Software Development :: Libraries :: Python Modules
Classifier: Topic :: Utilities
License-File: LICENSE.rst
Requires-Dist: a-cv-imwrite-imread-plus
Requires-Dist: numexpr
Requires-Dist: numpy
Requires-Dist: pandas
